dsfr/404.html
dsfr/__init__.py
dsfr/base.html
dsfr/breadcrumb.html
dsfr/dsfr.min.css
dsfr/dsfr.module.min.js
dsfr/dsfr.nomodule.min.js
dsfr/footer.html
dsfr/head.html
dsfr/header.html
dsfr/lateral.html
dsfr/main.html
dsfr/main_lateral.html
dsfr/main_no_lateral.html
dsfr/mkdocs_theme.yml
dsfr/nav.html
dsfr/newsletter.html
dsfr/notice.html
dsfr/prev-next-nav.html
dsfr/scripts.html
dsfr/search.html
dsfr/skiplinks.html
dsfr/summary.html
dsfr/tabs.html
dsfr/tags.html
dsfr/tags_index.html
dsfr/artwork/dark.svg
dsfr/artwork/light.svg
dsfr/artwork/system.svg
dsfr/artwork/background/ovoid.svg
dsfr/artwork/pictograms/accessibility/accessibility.svg
dsfr/artwork/pictograms/accessibility/ear-off.svg
dsfr/artwork/pictograms/accessibility/eye-off.svg
dsfr/artwork/pictograms/accessibility/mental-disabilities.svg
dsfr/artwork/pictograms/accessibility/wheelchair.svg
dsfr/artwork/pictograms/buildings/base.svg
dsfr/artwork/pictograms/buildings/city-hall.svg
dsfr/artwork/pictograms/buildings/companie.svg
dsfr/artwork/pictograms/buildings/factory.svg
dsfr/artwork/pictograms/buildings/house.svg
dsfr/artwork/pictograms/buildings/nuclear-plant.svg
dsfr/artwork/pictograms/buildings/school.svg
dsfr/artwork/pictograms/digital/application.svg
dsfr/artwork/pictograms/digital/avatar.svg
dsfr/artwork/pictograms/digital/calendar.svg
dsfr/artwork/pictograms/digital/coding.svg
dsfr/artwork/pictograms/digital/data-visualization.svg
dsfr/artwork/pictograms/digital/ecosystem.svg
dsfr/artwork/pictograms/digital/in-progress.svg
dsfr/artwork/pictograms/digital/innovation.svg
dsfr/artwork/pictograms/digital/internet.svg
dsfr/artwork/pictograms/digital/mail-send.svg
dsfr/artwork/pictograms/digital/search.svg
dsfr/artwork/pictograms/digital/self-training.svg
dsfr/artwork/pictograms/digital/smartphone.svg
dsfr/artwork/pictograms/document/archive.svg
dsfr/artwork/pictograms/document/binders.svg
dsfr/artwork/pictograms/document/conclusion.svg
dsfr/artwork/pictograms/document/contract.svg
mkdocs_dsfr-0.21.0.dist-info/licenses/LICENSE
mkdocs_dsfr-0.21.0.dist-info/METADATA
mkdocs_dsfr-0.21.0.dist-info/WHEEL
mkdocs_dsfr-0.21.0.dist-info/entry_points.txt
mkdocs_dsfr-0.21.0.dist-info/top_level.txt
mkdocs_dsfr-0.21.0.dist-info/RECORD
