Metadata-Version: 2.4
Name: mkdocs-dsfr
Version: 0.21.0
Summary: DSFR theme for Mkdocs
Author-email: Ministère Transition Écologique - DNUM <numerique-ecologie@developpement-durable.gouv.fr>
License-Expression: MIT
Project-URL: Homepage, https://gitlab-forge.din.developpement-durable.gouv.fr/pub/numeco/mkdocs-dsfr
Requires-Python: >=3.10
License-File: LICENSE
Requires-Dist: mkdocs>=1.4
Requires-Dist: pymdown-extensions>=10.4
Requires-Dist: Pygments>=2.17
Requires-Dist: dsfr-structure>=0.8.1
Requires-Dist: mkdocs-git-revision-date-localized-plugin>=1.4.5
Requires-Dist: mkdocs-rss-plugin>=1.17.4
Dynamic: license-file
